{
    "group": {
        "name": "OH MY GIRL",
        "type": "gg"
    },
    "members": [
        {
            "name": "Hyojung",
            "age": 30,
            "country": "Korean",
            "rating": 3,
            "stats": {
                "total_games": 7,
                "times_rerolled": 2,
                "times_bought": 5,
                "money_spent": -3
            }
        },
        {
            "name": "Mimi",
            "age": 29,
            "country": "Korean",
            "rating": 2,
            "stats": {
                "total_games": 5,
                "times_rerolled": 4,
                "times_bought": 5,
                "money_spent": -4
            }
        },
        {
            "name": "YooA",
            "age": 29,
            "country": "Korean",
            "rating": 4,
            "stats": {
                "total_games": 10,
                "times_rerolled": 2,
                "times_bought": 6,
                "money_spent": 0
            }
        },
        {
            "name": "Seunghee",
            "age": 29,
            "country": "Korean",
            "rating": 2,
            "stats": {
                "total_games": 9,
                "times_rerolled": 6,
                "times_bought": 7,
                "money_spent": -15
            }
        },
        {
            "name": "Yubin",
            "age": 27,
            "country": "Korean",
            "rating": 3,
            "stats": {
                "total_games": 6,
                "times_rerolled": 3,
                "times_bought": 5,
                "money_spent": -1
            }
        },
        {
            "name": "Arin",
            "age": 25,
            "country": "Korean",
            "rating": 4,
            "stats": {
                "total_games": 12,
                "times_rerolled": 3,
                "times_bought": 10,
                "money_spent": 3
            }
        },
        {
            "name": "JinE",
            "age": 30,
            "country": "Korean",
            "rating": 3,
            "stats": {
                "total_games": 5,
                "times_rerolled": 1,
                "times_bought": 4,
                "money_spent": 1
            }
        },
        {
            "name": "Jiho",
            "age": 27,
            "country": "Korean",
            "rating": 3,
            "stats": {
                "total_games": 5,
                "times_rerolled": 4,
                "times_bought": 2,
                "money_spent": 0
            }
        }
    ]
}